{
	"configurations" : 
	[
		{
			"directories" : 
			[
				{
					"build" : ".",
					"jsonFile" : "directory-.-Debug-d0094a50bb2071803777.json",
					"minimumCMakeVersion" : 
					{
						"string" : "3.17"
					},
					"projectIndex" : 0,
					"source" : ".",
					"targetIndexes" : 
					[
						0
					]
				}
			],
			"name" : "Debug",
			"projects" : 
			[
				{
					"directoryIndexes" : 
					[
						0
					],
					"name" : "0198Rob",
					"targetIndexes" : 
					[
						0
					]
				}
			],
			"targets" : 
			[
				{
					"directoryIndex" : 0,
					"id" : "0198Rob::@6890427a1f51a3e7e1df",
					"jsonFile" : "target-0198Rob-Debug-03904e026b6459b6c3db.json",
					"name" : "0198Rob",
					"projectIndex" : 0
				}
			]
		}
	],
	"kind" : "codemodel",
	"paths" : 
	{
		"build" : "D:/Algorithm/0198Rob/cmake-build-debug",
		"source" : "D:/Algorithm/0198Rob"
	},
	"version" : 
	{
		"major" : 2,
		"minor" : 4
	}
}
